excel2config/__init__.py
excel2config/excel2config.py
excel2config-2023.7.8.dist-info/LICENSE
excel2config-2023.7.8.dist-info/METADATA
excel2config-2023.7.8.dist-info/WHEEL
excel2config-2023.7.8.dist-info/entry_points.txt
excel2config-2023.7.8.dist-info/top_level.txt
excel2config-2023.7.8.dist-info/RECORD
