Metadata-Version: 2.1
Name: excel2config
Version: 2023.7.8
Summary: Generating network configuration with Excel sheets which include Jinja2 templates and data tables
Author: Umur Arslan
License: MIT License
Project-URL: Homepage, https://github.com/umurarslan/excel2config
Classifier: Programming Language :: Python :: 3
Classifier: License :: OSI Approved :: MIT License
Classifier: Operating System :: OS Independent
Requires-Python: >=3.9
License-File: LICENSE
Requires-Dist: Jinja2 (>=3.0)
Requires-Dist: openpyxl (>=3.0)
